.gitignore
.travis.yml
CHANGES.rst
README.rst
development.ini
requirements.txt
setup.cfg
setup.py
kotti_content_proxy/__init__.py
kotti_content_proxy/resources.py
kotti_content_proxy/views.py
kotti_content_proxy.egg-info/PKG-INFO
kotti_content_proxy.egg-info/SOURCES.txt
kotti_content_proxy.egg-info/dependency_links.txt
kotti_content_proxy.egg-info/not-zip-safe
kotti_content_proxy.egg-info/requires.txt
kotti_content_proxy.egg-info/top_level.txt
kotti_content_proxy/templates/view.pt
kotti_content_proxy/tests/conftest.py
kotti_content_proxy/tests/test_models.py
kotti_content_proxy/tests/test_views.py