Metadata-Version: 1.1
Name: kotti-content-proxy
Version: 0.4.1
Summary: A content type that proxies other content in a Kotti site
Home-page: https://github.com/Kotti
Author: Andreas Kaiser
Author-email: disko@binary-punks.com
License: BSD
Keywords: kotti addon
Platform: UNKNOWN
Classifier: Development Status :: 4 - Beta
Classifier: Environment :: Web Environment
Classifier: Framework :: Pyramid
Classifier: Intended Audience :: Developers
Classifier: License :: Repoze Public License
Classifier: Programming Language :: Python :: 2.7
Classifier: Programming Language :: Python
